CHANGELOG
LICENSE
MANIFEST.in
README.rst
setup.cfg
setup.py
YaCms.egg-info/PKG-INFO
YaCms.egg-info/SOURCES.txt
YaCms.egg-info/dependency_links.txt
YaCms.egg-info/entry_points.txt
YaCms.egg-info/not-zip-safe
YaCms.egg-info/requires.txt
YaCms.egg-info/top_level.txt
docs/admin-customization.rst
docs/blog-importing.rst
docs/caching-strategy.rst
docs/colophon.rst
docs/conf.py
docs/configuration.rst
docs/content-architecture.rst
docs/deployment.rst
docs/device-handling.rst
docs/docs_settings.py
docs/fabfile.rst
docs/frequently-asked-questions.rst
docs/index.rst
docs/inline-editing.rst
docs/model-customization.rst
docs/model-graph.rst
docs/multi-lingual-sites.rst
docs/multi-tenancy.rst
docs/overview.rst
docs/packages.rst
docs/search-engine.rst
docs/settings.rst
docs/twitter-integration.rst
docs/user-accounts.rst
docs/utilities.rst
docs/_ext/djangodocs.py
docs/img/dashboard.png
docs/img/graph-small.png
docs/img/graph.png
docs/locale/.placeholder
docs/mezzanine_theme/layout.html
docs/mezzanine_theme/theme.conf
docs/mezzanine_theme/static/mezzanine.css
yacms/__init__.py
yacms/urls.py
yacms/accounts/__init__.py
yacms/accounts/admin.py
yacms/accounts/defaults.py
yacms/accounts/forms.py
yacms/accounts/models.py
yacms/accounts/tests.py
yacms/accounts/urls.py
yacms/accounts/views.py
yacms/accounts/locale/ar/LC_MESSAGES/django.mo
yacms/accounts/locale/ar/LC_MESSAGES/django.po
yacms/accounts/locale/bg/LC_MESSAGES/django.mo
yacms/accounts/locale/bg/LC_MESSAGES/django.po
yacms/accounts/locale/ca/LC_MESSAGES/django.mo
yacms/accounts/locale/ca/LC_MESSAGES/django.po
yacms/accounts/locale/cs/LC_MESSAGES/django.mo
yacms/accounts/locale/cs/LC_MESSAGES/django.po
yacms/accounts/locale/da/LC_MESSAGES/django.mo
yacms/accounts/locale/da/LC_MESSAGES/django.po
yacms/accounts/locale/de/LC_MESSAGES/django.mo
yacms/accounts/locale/de/LC_MESSAGES/django.po
yacms/accounts/locale/en/LC_MESSAGES/django.mo
yacms/accounts/locale/en/LC_MESSAGES/django.po
yacms/accounts/locale/eo/LC_MESSAGES/django.mo
yacms/accounts/locale/eo/LC_MESSAGES/django.po
yacms/accounts/locale/es/LC_MESSAGES/django.mo
yacms/accounts/locale/es/LC_MESSAGES/django.po
yacms/accounts/locale/et/LC_MESSAGES/django.mo
