Metadata-Version: 1.1
Name: YaCms
Version: 4.2.2
Summary: An open source content management platform built using the Django framework.
Home-page: https://github.com/minhhoit/yacms
Author: Andrew Ho
Author-email: hoangminh.it4u@gmail.com
License: BSD
Download-URL: https://github.com/minhhoit/yacms/tarball/1.0
Platform: UNKNOWN
Classifier: Development Status :: 5 - Production/Stable
Classifier: Environment :: Web Environment
Classifier: Framework :: Django
Classifier: Intended Audience :: Developers
Classifier: License :: OSI Approved :: BSD License
Classifier: Operating System :: OS Independent
Classifier: Programming Language :: Python
Classifier: Programming Language :: Python :: 2.7
Classifier: Programming Language :: Python :: 3
Classifier: Programming Language :: Python :: 3.4
Classifier: Programming Language :: Python :: 3.5
Classifier: Topic :: Software Development :: Libraries :: Application Frameworks
Classifier: Topic :: Software Development :: Libraries :: Python Modules
